jupyterpost/__init__.py
jupyterpost/jupyterpost.py
jupyterpost-0.0.1.dist-info/entry_points.txt
jupyterpost-0.0.1.dist-info/LICENSE
jupyterpost-0.0.1.dist-info/WHEEL
jupyterpost-0.0.1.dist-info/METADATA
jupyterpost-0.0.1.dist-info/RECORD
