Metadata-Version: 2.1
Name: jupyterpost
Version: 0.0.1
Summary: Jupyterpost: Jupyterhub service for posting to Mattermost.
Author-email: Anton Akhmerov <jupyterpost@antonakhmerov.org>
Requires-Python: >=3.10
Classifier: Programming Language :: Python :: 3
Classifier: License :: OSI Approved :: MIT License
Classifier: Operating System :: OS Independent
Requires-Dist: jupyterhub >= 3.0.0
Requires-Dist: httpx >= 0.19.0
Project-URL: Bug Tracker, https://gitlab.kwant-project.org/qt/jupyterpost/-/issues
Project-URL: Homepage, https://gitlab.kwant-project.org/qt/jupyterpost
